TFLsTool/CombineRTF.py
TFLsTool/CompletenessReport.py
TFLsTool/ExtractShellToTracker.py
TFLsTool/__init__.py
TFLsTool-0.0.5.dist-info/METADATA
TFLsTool-0.0.5.dist-info/WHEEL
TFLsTool-0.0.5.dist-info/top_level.txt
TFLsTool-0.0.5.dist-info/RECORD
