Metadata-Version: 2.1
Name: TFLsTool
Version: 0.0.5
Summary: This is a toolkit related to TFL (Tables, Figures, and Listings) generation in the field of clinical biostatistics for pharmaceuticals.
Home-page: https://github/allensrj/
Author: allensrj
Author-email: allensrj@qq.com
License: MIT
Requires-Dist: pandas (>=2.2.1)
Requires-Dist: numpy (>=1.21.0)
Requires-Dist: python-docx (==0.8.11)
Requires-Dist: zhon (==2.0.2)
Requires-Dist: openpyxl (>=3.1.0)
Requires-Dist: matplotlib
